{
"responses":[
	{
	  "ResponseID" : "R_3LbscEduIaqGedQ",
	  "ResponseSet" : "Default Response Set",
	  "IPAddress" : "",
	  "StartDate" : "2018-03-01 09:58:48",
	  "EndDate" : "2018-03-01 09:59:19",
	  "RecipientLastName" : "",
	  "RecipientFirstName" : "",
	  "RecipientEmail" : "",
	  "ExternalDataReference" : "",
	  "Finished" : "1",
	  "Status" : "1",
	  "PROJECT_NAME" : "",
	  "PROJECT_NUMBER" : "",
	  "CSS_ID" : "",
	  "CONSENT" : "1",
	  "Q17" : "",
	  "CONSENT_TIME_1" : "",
	  "CONSENT_TIME_2" : "",
	  "CONSENT_TIME_3" : "",
	  "CONSENT_TIME_4" : "",
	  "Q2" : "18",
	  "Q3" : "1",
	  "Q12" : "",
	  "Q14#1_1_1_TEXT" : "",
	  "Q14#1_2_1_TEXT" : "",
	  "Q14#1_3_1_TEXT" : "",
	  "Q14#1_4_1_TEXT" : "",
	  "Q14#1_5_1_TEXT" : "",
	  "Q14#1_6_1_TEXT" : "",
	  "Q14#1_7_1_TEXT" : "",
	  "Q14#2_1_1_TEXT" : "",
	  "Q14#2_2_1_TEXT" : "",
	  "Q14#2_3_1_TEXT" : "",
	  "Q14#2_4_1_TEXT" : "",
	  "Q14#2_5_1_TEXT" : "",
	  "Q14#2_6_1_TEXT" : "",
	  "Q14#2_7_1_TEXT" : "",
	  "Q14#3_1_1_TEXT" : "",
	  "Q14#3_2_1_TEXT" : "",
	  "Q14#3_3_1_TEXT" : "",
	  "Q14#3_4_1_TEXT" : "",
	  "Q14#3_5_1_TEXT" : "",
	  "Q14#3_6_1_TEXT" : "",
	  "Q14#3_7_1_TEXT" : "",
	  "Q14#4_1_1" : "",
	  "Q14#4_1_2" : "",
	  "Q14#4_1_3" : "",
	  "Q14#4_1_4" : "",
	  "Q14#4_1_5" : "",
	  "Q14#4_1_6" : "",
	  "Q14#4_1_7" : "",
	  "Q14#4_1_8" : "",
	  "Q14#4_1_9" : "",
	  "Q14#4_2_1" : "",
	  "Q14#4_2_2" : "",
	  "Q14#4_2_3" : "",
	  "Q14#4_2_4" : "",
	  "Q14#4_2_5" : "",
	  "Q14#4_2_6" : "",
	  "Q14#4_2_7" : "",
	  "Q14#4_2_8" : "",
	  "Q14#4_2_9" : "",
	  "Q14#4_3_1" : "",
	  "Q14#4_3_2" : "",
	  "Q14#4_3_3" : "",
	  "Q14#4_3_4" : "",
	  "Q14#4_3_5" : "",
	  "Q14#4_3_6" : "",
	  "Q14#4_3_7" : "",
	  "Q14#4_3_8" : "",
	  "Q14#4_3_9" : "",
	  "Q14#4_4_1" : "",
	  "Q14#4_4_2" : "",
	  "Q14#4_4_3" : "",
	  "Q14#4_4_4" : "",
	  "Q14#4_4_5" : "",
	  "Q14#4_4_6" : "",
	  "Q14#4_4_7" : "",
	  "Q14#4_4_8" : "",
	  "Q14#4_4_9" : "",
	  "Q14#4_5_1" : "",
	  "Q14#4_5_2" : "",
	  "Q14#4_5_3" : "",
	  "Q14#4_5_4" : "",
	  "Q14#4_5_5" : "",
	  "Q14#4_5_6" : "",
	  "Q14#4_5_7" : "",
	  "Q14#4_5_8" : "",
	  "Q14#4_5_9" : "",
	  "Q14#4_6_1" : "",
	  "Q14#4_6_2" : "",
	  "Q14#4_6_3" : "",
	  "Q14#4_6_4" : "",
	  "Q14#4_6_5" : "",
	  "Q14#4_6_6" : "",
	  "Q14#4_6_7" : "",
	  "Q14#4_6_8" : "",
	  "Q14#4_6_9" : "",
	  "Q14#4_7_1" : "",
	  "Q14#4_7_2" : "",
	  "Q14#4_7_3" : "",
	  "Q14#4_7_4" : "",
	  "Q14#4_7_5" : "",
	  "Q14#4_7_6" : "",
	  "Q14#4_7_7" : "",
	  "Q14#4_7_8" : "",
	  "Q14#4_7_9" : "",
	  "Q16_1" : "",
	  "Q16_2" : "",
	  "Q16_3" : "",
	  "SCREEN TIME_1" : "",
	  "SCREEN TIME_2" : "",
	  "SCREEN TIME_3" : "",
	  "SCREEN TIME_4" : "",
	  "Q4" : "1",
	  "Q8" : "",
	  "Q13_1" : "",
	  "Q13_2" : "",
	  "Q13_3" : "",
	  "Q5" : "Shelly",
	  "Q6_1" : "2",
	  "Q6_2" : "2",
	  "Q6_3" : "3",
	  "Q6_4" : "1",
	  "Q6_5" : "2",
	  "Q7_1" : "2",
	  "Q7_2" : "",
	  "Q7_3" : "",
	  "Q9" : "1",
	  "LocationLatitude" : "41.887603759766",
	  "LocationLongitude" : "-87.63680267334",
	  "LocationAccuracy" : "-1"
	},
	{
	  "ResponseID" : "R_2XnvzBus5et5Cez",
	  "ResponseSet" : "Default Response Set",
	  "IPAddress" : "",
	  "StartDate" : "2018-03-01 09:59:21",
	  "EndDate" : "2018-03-01 09:59:50",
	  "RecipientLastName" : "",
	  "RecipientFirstName" : "",
	  "RecipientEmail" : "",
	  "ExternalDataReference" : "",
	  "Finished" : "1",
	  "Status" : "1",
	  "PROJECT_NAME" : "",
	  "PROJECT_NUMBER" : "",
	  "CSS_ID" : "",
	  "CONSENT" : "1",
	  "Q17" : "",
	  "CONSENT_TIME_1" : "",
	  "CONSENT_TIME_2" : "",
	  "CONSENT_TIME_3" : "",
	  "CONSENT_TIME_4" : "",
	  "Q2" : "40",
	  "Q3" : "2",
	  "Q12" : "",
	  "Q14#1_1_1_TEXT" : "",
	  "Q14#1_2_1_TEXT" : "",
	  "Q14#1_3_1_TEXT" : "",
	  "Q14#1_4_1_TEXT" : "",
	  "Q14#1_5_1_TEXT" : "",
	  "Q14#1_6_1_TEXT" : "",
	  "Q14#1_7_1_TEXT" : "",
	  "Q14#2_1_1_TEXT" : "",
	  "Q14#2_2_1_TEXT" : "",
	  "Q14#2_3_1_TEXT" : "",
	  "Q14#2_4_1_TEXT" : "",
	  "Q14#2_5_1_TEXT" : "",
	  "Q14#2_6_1_TEXT" : "",
	  "Q14#2_7_1_TEXT" : "",
	  "Q14#3_1_1_TEXT" : "",
	  "Q14#3_2_1_TEXT" : "",
	  "Q14#3_3_1_TEXT" : "",
	  "Q14#3_4_1_TEXT" : "",
	  "Q14#3_5_1_TEXT" : "",
	  "Q14#3_6_1_TEXT" : "",
	  "Q14#3_7_1_TEXT" : "",
	  "Q14#4_1_1" : "",
	  "Q14#4_1_2" : "",
	  "Q14#4_1_3" : "",
	  "Q14#4_1_4" : "",
	  "Q14#4_1_5" : "",
	  "Q14#4_1_6" : "",
	  "Q14#4_1_7" : "",
	  "Q14#4_1_8" : "",
	  "Q14#4_1_9" : "",
	  "Q14#4_2_1" : "",
	  "Q14#4_2_2" : "",
	  "Q14#4_2_3" : "",
	  "Q14#4_2_4" : "",
	  "Q14#4_2_5" : "",
	  "Q14#4_2_6" : "",
	  "Q14#4_2_7" : "",
	  "Q14#4_2_8" : "",
	  "Q14#4_2_9" : "",
	  "Q14#4_3_1" : "",
	  "Q14#4_3_2" : "",
	  "Q14#4_3_3" : "",
	  "Q14#4_3_4" : "",
	  "Q14#4_3_5" : "",
	  "Q14#4_3_6" : "",
	  "Q14#4_3_7" : "",
	  "Q14#4_3_8" : "",
	  "Q14#4_3_9" : "",
	  "Q14#4_4_1" : "",
	  "Q14#4_4_2" : "",
	  "Q14#4_4_3" : "",
	  "Q14#4_4_4" : "",
	  "Q14#4_4_5" : "",
	  "Q14#4_4_6" : "",
	  "Q14#4_4_7" : "",
	  "Q14#4_4_8" : "",
	  "Q14#4_4_9" : "",
	  "Q14#4_5_1" : "",
	  "Q14#4_5_2" : "",
	  "Q14#4_5_3" : "",
	  "Q14#4_5_4" : "",
	  "Q14#4_5_5" : "",
	  "Q14#4_5_6" : "",
	  "Q14#4_5_7" : "",
	  "Q14#4_5_8" : "",
	  "Q14#4_5_9" : "",
	  "Q14#4_6_1" : "",
	  "Q14#4_6_2" : "",
	  "Q14#4_6_3" : "",
	  "Q14#4_6_4" : "",
	  "Q14#4_6_5" : "",
	  "Q14#4_6_6" : "",
	  "Q14#4_6_7" : "",
	  "Q14#4_6_8" : "",
	  "Q14#4_6_9" : "",
	  "Q14#4_7_1" : "",
	  "Q14#4_7_2" : "",
	  "Q14#4_7_3" : "",
	  "Q14#4_7_4" : "",
	  "Q14#4_7_5" : "",
	  "Q14#4_7_6" : "",
	  "Q14#4_7_7" : "",
	  "Q14#4_7_8" : "",
	  "Q14#4_7_9" : "",
	  "Q16_1" : "",
	  "Q16_2" : "",
	  "Q16_3" : "",
	  "SCREEN TIME_1" : "",
	  "SCREEN TIME_2" : "",
	  "SCREEN TIME_3" : "",
	  "SCREEN TIME_4" : "",
	  "Q4" : "4",
	  "Q8" : "",
	  "Q13_1" : "",
	  "Q13_2" : "",
	  "Q13_3" : "",
	  "Q5" : "Batman",
	  "Q6_1" : "3",
	  "Q6_2" : "3",
	  "Q6_3" : "3",
	  "Q6_4" : "3",
	  "Q6_5" : "3",
	  "Q7_1" : "2",
	  "Q7_2" : "2",
	  "Q7_3" : "1",
	  "Q9" : "1",
	  "LocationLatitude" : "41.887603759766",
	  "LocationLongitude" : "-87.63680267334",
	  "LocationAccuracy" : "-1"
	},
	{
	  "ResponseID" : "R_2P7rml17DxMhZ0L",
	  "ResponseSet" : "Default Response Set",
	  "IPAddress" : "",
	  "StartDate" : "2018-03-01 09:59:58",
	  "EndDate" : "2018-03-01 10:00:22",
	  "RecipientLastName" : "",
	  "RecipientFirstName" : "",
	  "RecipientEmail" : "",
	  "ExternalDataReference" : "",
	  "Finished" : "1",
	  "Status" : "1",
	  "PROJECT_NAME" : "",
	  "PROJECT_NUMBER" : "",
	  "CSS_ID" : "",
	  "CONSENT" : "1",
	  "Q17" : "",
	  "CONSENT_TIME_1" : "",
	  "CONSENT_TIME_2" : "",
	  "CONSENT_TIME_3" : "",
	  "CONSENT_TIME_4" : "",
	  "Q2" : "23",
	  "Q3" : "3",
	  "Q12" : "",
	  "Q14#1_1_1_TEXT" : "",
	  "Q14#1_2_1_TEXT" : "",
	  "Q14#1_3_1_TEXT" : "",
	  "Q14#1_4_1_TEXT" : "",
	  "Q14#1_5_1_TEXT" : "",
	  "Q14#1_6_1_TEXT" : "",
	  "Q14#1_7_1_TEXT" : "",
	  "Q14#2_1_1_TEXT" : "",
	  "Q14#2_2_1_TEXT" : "",
	  "Q14#2_3_1_TEXT" : "",
	  "Q14#2_4_1_TEXT" : "",
	  "Q14#2_5_1_TEXT" : "",
	  "Q14#2_6_1_TEXT" : "",
	  "Q14#2_7_1_TEXT" : "",
	  "Q14#3_1_1_TEXT" : "",
	  "Q14#3_2_1_TEXT" : "",
	  "Q14#3_3_1_TEXT" : "",
	  "Q14#3_4_1_TEXT" : "",
	  "Q14#3_5_1_TEXT" : "",
	  "Q14#3_6_1_TEXT" : "",
	  "Q14#3_7_1_TEXT" : "",
	  "Q14#4_1_1" : "",
	  "Q14#4_1_2" : "",
	  "Q14#4_1_3" : "",
	  "Q14#4_1_4" : "",
	  "Q14#4_1_5" : "",
	  "Q14#4_1_6" : "",
	  "Q14#4_1_7" : "",
	  "Q14#4_1_8" : "",
	  "Q14#4_1_9" : "",
	  "Q14#4_2_1" : "",
	  "Q14#4_2_2" : "",
	  "Q14#4_2_3" : "",
	  "Q14#4_2_4" : "",
	  "Q14#4_2_5" : "",
	  "Q14#4_2_6" : "",
	  "Q14#4_2_7" : "",
	  "Q14#4_2_8" : "",
	  "Q14#4_2_9" : "",
	  "Q14#4_3_1" : "",
	  "Q14#4_3_2" : "",
	  "Q14#4_3_3" : "",
	  "Q14#4_3_4" : "",
	  "Q14#4_3_5" : "",
	  "Q14#4_3_6" : "",
	  "Q14#4_3_7" : "",
	  "Q14#4_3_8" : "",
	  "Q14#4_3_9" : "",
	  "Q14#4_4_1" : "",
	  "Q14#4_4_2" : "",
	  "Q14#4_4_3" : "",
	  "Q14#4_4_4" : "",
	  "Q14#4_4_5" : "",
	  "Q14#4_4_6" : "",
	  "Q14#4_4_7" : "",
	  "Q14#4_4_8" : "",
	  "Q14#4_4_9" : "",
	  "Q14#4_5_1" : "",
	  "Q14#4_5_2" : "",
	  "Q14#4_5_3" : "",
	  "Q14#4_5_4" : "",
	  "Q14#4_5_5" : "",
	  "Q14#4_5_6" : "",
	  "Q14#4_5_7" : "",
	  "Q14#4_5_8" : "",
	  "Q14#4_5_9" : "",
	  "Q14#4_6_1" : "",
	  "Q14#4_6_2" : "",
	  "Q14#4_6_3" : "",
	  "Q14#4_6_4" : "",
	  "Q14#4_6_5" : "",
	  "Q14#4_6_6" : "",
	  "Q14#4_6_7" : "",
	  "Q14#4_6_8" : "",
	  "Q14#4_6_9" : "",
	  "Q14#4_7_1" : "",
	  "Q14#4_7_2" : "",
	  "Q14#4_7_3" : "",
	  "Q14#4_7_4" : "",
	  "Q14#4_7_5" : "",
	  "Q14#4_7_6" : "",
	  "Q14#4_7_7" : "",
	  "Q14#4_7_8" : "",
	  "Q14#4_7_9" : "",
	  "Q16_1" : "",
	  "Q16_2" : "",
	  "Q16_3" : "",
	  "SCREEN TIME_1" : "",
	  "SCREEN TIME_2" : "",
	  "SCREEN TIME_3" : "",
	  "SCREEN TIME_4" : "",
	  "Q4" : "3",
	  "Q8" : "",
	  "Q13_1" : "",
	  "Q13_2" : "",
	  "Q13_3" : "",
	  "Q5" : "Kelly",
	  "Q6_1" : "2",
	  "Q6_2" : "2",
	  "Q6_3" : "",
	  "Q6_4" : "",
	  "Q6_5" : "",
	  "Q7_1" : "",
	  "Q7_2" : "",
	  "Q7_3" : "",
	  "Q9" : "1",
	  "LocationLatitude" : "41.887603759766",
	  "LocationLongitude" : "-87.63680267334",
	  "LocationAccuracy" : "-1"
	},
	{
	  "ResponseID" : "R_1NDKof0HmijJM1Z",
	  "ResponseSet" : "Default Response Set",
	  "IPAddress" : "",
	  "StartDate" : "2018-03-01 10:00:25",
	  "EndDate" : "2018-03-01 10:00:52",
	  "RecipientLastName" : "",
	  "RecipientFirstName" : "",
	  "RecipientEmail" : "",
	  "ExternalDataReference" : "",
	  "Finished" : "1",
	  "Status" : "1",
	  "PROJECT_NAME" : "",
	  "PROJECT_NUMBER" : "",
	  "CSS_ID" : "",
	  "CONSENT" : "1",
	  "Q17" : "",
	  "CONSENT_TIME_1" : "",
	  "CONSENT_TIME_2" : "",
	  "CONSENT_TIME_3" : "",
	  "CONSENT_TIME_4" : "",
	  "Q2" : "24",
	  "Q3" : "1",
	  "Q12" : "",
	  "Q14#1_1_1_TEXT" : "",
	  "Q14#1_2_1_TEXT" : "",
	  "Q14#1_3_1_TEXT" : "",
	  "Q14#1_4_1_TEXT" : "",
	  "Q14#1_5_1_TEXT" : "",
	  "Q14#1_6_1_TEXT" : "",
	  "Q14#1_7_1_TEXT" : "",
	  "Q14#2_1_1_TEXT" : "",
	  "Q14#2_2_1_TEXT" : "",
	  "Q14#2_3_1_TEXT" : "",
	  "Q14#2_4_1_TEXT" : "",
	  "Q14#2_5_1_TEXT" : "",
	  "Q14#2_6_1_TEXT" : "",
	  "Q14#2_7_1_TEXT" : "",
	  "Q14#3_1_1_TEXT" : "",
	  "Q14#3_2_1_TEXT" : "",
	  "Q14#3_3_1_TEXT" : "",
	  "Q14#3_4_1_TEXT" : "",
	  "Q14#3_5_1_TEXT" : "",
	  "Q14#3_6_1_TEXT" : "",
	  "Q14#3_7_1_TEXT" : "",
	  "Q14#4_1_1" : "",
	  "Q14#4_1_2" : "",
	  "Q14#4_1_3" : "",
	  "Q14#4_1_4" : "",
	  "Q14#4_1_5" : "",
	  "Q14#4_1_6" : "",
	  "Q14#4_1_7" : "",
	  "Q14#4_1_8" : "",
	  "Q14#4_1_9" : "",
	  "Q14#4_2_1" : "",
	  "Q14#4_2_2" : "",
	  "Q14#4_2_3" : "",
	  "Q14#4_2_4" : "",
	  "Q14#4_2_5" : "",
	  "Q14#4_2_6" : "",
	  "Q14#4_2_7" : "",
	  "Q14#4_2_8" : "",
	  "Q14#4_2_9" : "",
	  "Q14#4_3_1" : "",
	  "Q14#4_3_2" : "",
	  "Q14#4_3_3" : "",
	  "Q14#4_3_4" : "",
	  "Q14#4_3_5" : "",
	  "Q14#4_3_6" : "",
	  "Q14#4_3_7" : "",
	  "Q14#4_3_8" : "",
	  "Q14#4_3_9" : "",
	  "Q14#4_4_1" : "",
	  "Q14#4_4_2" : "",
	  "Q14#4_4_3" : "",
	  "Q14#4_4_4" : "",
	  "Q14#4_4_5" : "",
	  "Q14#4_4_6" : "",
	  "Q14#4_4_7" : "",
	  "Q14#4_4_8" : "",
	  "Q14#4_4_9" : "",
	  "Q14#4_5_1" : "",
	  "Q14#4_5_2" : "",
	  "Q14#4_5_3" : "",
	  "Q14#4_5_4" : "",
	  "Q14#4_5_5" : "",
	  "Q14#4_5_6" : "",
	  "Q14#4_5_7" : "",
	  "Q14#4_5_8" : "",
	  "Q14#4_5_9" : "",
	  "Q14#4_6_1" : "",
	  "Q14#4_6_2" : "",
	  "Q14#4_6_3" : "",
	  "Q14#4_6_4" : "",
	  "Q14#4_6_5" : "",
	  "Q14#4_6_6" : "",
	  "Q14#4_6_7" : "",
	  "Q14#4_6_8" : "",
	  "Q14#4_6_9" : "",
	  "Q14#4_7_1" : "",
	  "Q14#4_7_2" : "",
	  "Q14#4_7_3" : "",
	  "Q14#4_7_4" : "",
	  "Q14#4_7_5" : "",
	  "Q14#4_7_6" : "",
	  "Q14#4_7_7" : "",
	  "Q14#4_7_8" : "",
	  "Q14#4_7_9" : "",
	  "Q16_1" : "",
	  "Q16_2" : "",
	  "Q16_3" : "",
	  "SCREEN TIME_1" : "",
	  "SCREEN TIME_2" : "",
	  "SCREEN TIME_3" : "",
	  "SCREEN TIME_4" : "",
	  "Q4" : "2",
	  "Q8" : "",
	  "Q13_1" : "",
	  "Q13_2" : "",
	  "Q13_3" : "",
	  "Q5" : "Botter Bottttt",
	  "Q6_1" : "3",
	  "Q6_2" : "3",
	  "Q6_3" : "2",
	  "Q6_4" : "1",
	  "Q6_5" : "1",
	  "Q7_1" : "2",
	  "Q7_2" : "1",
	  "Q7_3" : "2",
	  "Q9" : "1",
	  "LocationLatitude" : "41.887603759766",
	  "LocationLongitude" : "-87.63680267334",
	  "LocationAccuracy" : "-1"
	},
	{
	  "ResponseID" : "R_2aQNrUiXaeBkOnm",
	  "ResponseSet" : "Default Response Set",
	  "IPAddress" : "",
	  "StartDate" : "2018-03-01 11:32:06",
	  "EndDate" : "2018-03-01 11:33:05",
	  "RecipientLastName" : "",
	  "RecipientFirstName" : "",
	  "RecipientEmail" : "",
	  "ExternalDataReference" : "",
	  "Finished" : "1",
	  "Status" : "1",
	  "PROJECT_NAME" : "",
	  "PROJECT_NUMBER" : "",
	  "CSS_ID" : "",
	  "CONSENT" : "1",
	  "Q17" : "",
	  "CONSENT_TIME_1" : "",
	  "CONSENT_TIME_2" : "",
	  "CONSENT_TIME_3" : "",
	  "CONSENT_TIME_4" : "",
	  "Q2" : "18",
	  "Q3" : "3",
	  "Q12" : "",
	  "Q14#1_1_1_TEXT" : "",
	  "Q14#1_2_1_TEXT" : "",
	  "Q14#1_3_1_TEXT" : "",
	  "Q14#1_4_1_TEXT" : "",
	  "Q14#1_5_1_TEXT" : "",
	  "Q14#1_6_1_TEXT" : "",
	  "Q14#1_7_1_TEXT" : "",
	  "Q14#2_1_1_TEXT" : "",
	  "Q14#2_2_1_TEXT" : "",
	  "Q14#2_3_1_TEXT" : "",
	  "Q14#2_4_1_TEXT" : "",
	  "Q14#2_5_1_TEXT" : "",
	  "Q14#2_6_1_TEXT" : "",
	  "Q14#2_7_1_TEXT" : "",
	  "Q14#3_1_1_TEXT" : "",
	  "Q14#3_2_1_TEXT" : "",
	  "Q14#3_3_1_TEXT" : "",
	  "Q14#3_4_1_TEXT" : "",
	  "Q14#3_5_1_TEXT" : "",
	  "Q14#3_6_1_TEXT" : "",
	  "Q14#3_7_1_TEXT" : "",
	  "Q14#4_1_1" : "",
	  "Q14#4_1_2" : "",
	  "Q14#4_1_3" : "",
	  "Q14#4_1_4" : "",
	  "Q14#4_1_5" : "",
	  "Q14#4_1_6" : "",
	  "Q14#4_1_7" : "",
	  "Q14#4_1_8" : "",
	  "Q14#4_1_9" : "",
	  "Q14#4_2_1" : "",
	  "Q14#4_2_2" : "",
	  "Q14#4_2_3" : "",
	  "Q14#4_2_4" : "",
	  "Q14#4_2_5" : "",
	  "Q14#4_2_6" : "",
	  "Q14#4_2_7" : "",
	  "Q14#4_2_8" : "",
	  "Q14#4_2_9" : "",
	  "Q14#4_3_1" : "",
	  "Q14#4_3_2" : "",
	  "Q14#4_3_3" : "",
	  "Q14#4_3_4" : "",
	  "Q14#4_3_5" : "",
	  "Q14#4_3_6" : "",
	  "Q14#4_3_7" : "",
	  "Q14#4_3_8" : "",
	  "Q14#4_3_9" : "",
	  "Q14#4_4_1" : "",
	  "Q14#4_4_2" : "",
	  "Q14#4_4_3" : "",
	  "Q14#4_4_4" : "",
	  "Q14#4_4_5" : "",
	  "Q14#4_4_6" : "",
	  "Q14#4_4_7" : "",
	  "Q14#4_4_8" : "",
	  "Q14#4_4_9" : "",
	  "Q14#4_5_1" : "",
	  "Q14#4_5_2" : "",
	  "Q14#4_5_3" : "",
	  "Q14#4_5_4" : "",
	  "Q14#4_5_5" : "",
	  "Q14#4_5_6" : "",
	  "Q14#4_5_7" : "",
	  "Q14#4_5_8" : "",
	  "Q14#4_5_9" : "",
	  "Q14#4_6_1" : "",
	  "Q14#4_6_2" : "",
	  "Q14#4_6_3" : "",
	  "Q14#4_6_4" : "",
	  "Q14#4_6_5" : "",
	  "Q14#4_6_6" : "",
	  "Q14#4_6_7" : "",
	  "Q14#4_6_8" : "",
	  "Q14#4_6_9" : "",
	  "Q14#4_7_1" : "",
	  "Q14#4_7_2" : "",
	  "Q14#4_7_3" : "",
	  "Q14#4_7_4" : "",
	  "Q14#4_7_5" : "",
	  "Q14#4_7_6" : "",
	  "Q14#4_7_7" : "",
	  "Q14#4_7_8" : "",
	  "Q14#4_7_9" : "",
	  "Q16_1" : "",
	  "Q16_2" : "",
	  "Q16_3" : "",
	  "SCREEN TIME_1" : "",
	  "SCREEN TIME_2" : "",
	  "SCREEN TIME_3" : "",
	  "SCREEN TIME_4" : "",
	  "Q4" : "3",
	  "Q8" : "",
	  "Q13_1" : "",
	  "Q13_2" : "",
	  "Q13_3" : "",
	  "Q5" : "Picard",
	  "Q6_1" : "1",
	  "Q6_2" : "2",
	  "Q6_3" : "1",
	  "Q6_4" : "1",
	  "Q6_5" : "3",
	  "Q7_1" : "3",
	  "Q7_2" : "2",
	  "Q7_3" : "3",
	  "Q9" : "1",
	  "LocationLatitude" : "41.887603759766",
	  "LocationLongitude" : "-87.63680267334",
	  "LocationAccuracy" : "-1"
	}
]}